itemie/__init__.py
itemie/analyse/__init__.py
itemie/analyse/topic.py
itemie/core/__init__.py
itemie/core/convert.py
itemie/core/group.py
itemie/core/item.py
itemie/report/__init__.py
itemie/report/wordcloud.py
itemie/utils/__init__.py
itemie-0.0.5.dist-info/METADATA
itemie-0.0.5.dist-info/WHEEL
itemie-0.0.5.dist-info/licenses/LICENSE
itemie-0.0.5.dist-info/RECORD
